sazonal
