Metadata-Version: 2.1
Name: cptec-sazonal
Version: 0.0.2
Summary: Módulo para distribuição do Modelo SubSazonal do CPTEC.
Home-page: https://sazonal.readthedocs.io/en/latest/index.html
Author: Framework CPTEC
Author-email: frameworkcptec@gmail.com
License: MIT
Project-URL: Código fonte, https://github.com/framework-CPTEC/Sazonal
Project-URL: Download, https://github.com/framework-CPTEC/Sazonal
Keywords: recuperação de dados climáticos
Classifier: Development Status :: 5 - Production/Stable
Classifier: Intended Audience :: Developers
Classifier: License :: OSI Approved :: MIT License
Classifier: Natural Language :: Portuguese (Brazilian)
Classifier: Operating System :: OS Independent
Classifier: Topic :: Software Development :: Internationalization
Classifier: Topic :: Scientific/Engineering :: Physics
Requires-Python: >=3.10
Requires-Dist: numpy
Requires-Dist: pandas
Requires-Dist: xarray
Requires-Dist: requests
Requires-Dist: matplotlib
Requires-Dist: scipy
Requires-Dist: netCDF4
